{
    "御火芭蕉扇": "御火芭蕉扇\n冷却:32s-31s-29.5s\n系数:平推5.27~6.80 极限12.44",
    "炎宿·朱雀": "炎宿·朱雀\n冷却:36s-35s-33.5s\n系数:平推7.10~8.43 极限9.76",
    "龙神飨宴": "龙神飨宴\n冷却:40s-39s-37.5s\n系数:0.36/发 上限9.7",
    "祝融": "祝融\n冷却:36s-35s-33.5s\n系数:3.8/2.4/2.0/1.8 共10.0",
    "神炎杖": "神炎杖\n冷却:38s-37s-35.5s\n系数:2.64/发 上限10.56",
    "织炎": "织炎\n冷却:34.5s-33.5s-32s\n系数:3.125/2.15*2/3.375 共10.8",
    "赤焰龙息": "赤焰龙息\n冷却:36s-35s-33.5s(46s-44.5s-42s)\n系数:11.29/12.59(人类12.42/13.85)",
    "怒鲤双生": "怒鲤双生\n冷却:36s-35s-33.5s\n系数:12.76/13.22(恶龙14.04/14.55)",

    "爱疯XXX": "爱疯XXX\n冷却:38s-37s-35.5s\n系数:清屏6.1 触碰0.6+0.2*n 极限12.26",
    "漩雷一文字": "漩雷一文字\n冷却:40s-39s-37.5s\n系数:跟踪1.1/发 极限12.99(19.38)",
    "雷宿·麒麟": "雷宿·麒麟\n冷却:35s-34s-32.5s\n系数:0.29*26 上限7.54",
    "三日月雷切": "三日月雷切\n冷却:36s-35s-33.5s\n系数:平推8.91~9.57 极限11.28",
    "雷鸣剑": "雷鸣剑\n冷却:36s-35s-33.5s\n系数:10.48",
    "雷狱光剑": "雷狱光剑\n冷却:36s-35s-33.5s\n系数:10.31(妖鬼11.35)",
    "百雷·拂晓": "百雷·拂晓\n冷却:36s-35s-33.5s\n系数:小剑6 大剑5.3 上限11.3(机械12.43)",
    "八岐断雷枪":"八岐断雷枪\n冷却:36s-35s-33.5s\n系数:防御0.4*30 攻击11.91(人类13.10)",
    "紫电白虹":"紫电白虹\n冷却:36s-35s-33.5s\n系数:13.0/13.7(野兽14.3/15.07)",

    "真·凌玉弓": "真·凌玉弓\n冷却:35s-34s-32.5s\n系数:5.17/3.025/3.08 上限11.275",
    "天晶苦无": "天晶苦无\n冷却:36s-35s-33.5s(72s-70s-67s)\n系数:5.48/3.36/2.4",
    "神使·沧溟": "神使·沧溟\n冷却:40s-39s-37.5s\n系数:平推6.89~10.0 上限13.74",
    "冰岚折扇": "冰岚折扇\n冷却:36s-35s-33.5s\n系数:9.75 上限11.47",
    "广罗天寒": "广罗天寒\n冷却:34.5s-33.5s-31s\n系数:聚拢9.3 扩散11.0",
    "如龙临渊": "如龙临渊\n冷却:36s-35s-33.5s\n系数:10.66(恶龙11.72)",
    "断潮": "断潮\n冷却:36s-35s-33.5s\n系数:平推8.1~8.8 极限10.92",
    "苍雪祝神铃": "苍雪祝神铃\n冷却:36s-35s-33.5s\n系数:平推9.50~11.8 极限12.16",
    "龙毫笔": "龙毫笔\n冷却:36s-35s-33.5s\n系数:11.82(妖鬼13.0)",
    "伏溟九渊": "伏溟九渊\n冷却:36s-35s-33.5s\n系数:平推13.25/13.81 贴脸13.78/14.36(妖鬼平推14.57/15.19 贴脸15.16/15.8)",

    "鬼泪村正": "鬼泪村正\n冷却:33s-32s-30.5s\n系数:2.09/刀 极限10.45",
    "天音灵箫": "天音灵箫\n冷却:40s-39s-37.5s\n系数:清屏6.6 触碰0.8",
    "风妖镰鼬": "风妖镰鼬\n冷却:35s-34s-32.5s\n系数:平推4.16~6.41 极限11.92",
    "风宿·苍龙": "风宿·苍龙\n冷却:36s-35s-33.5s\n系数:大箭7.80 小箭1.35 极限11.0",
    "苍月战刃": "苍月战刃\n冷却:36s-35s-33.5s\n系数:平推5.43~10.06 极限13.54",
    "亡魂之音": "亡魂之音\n冷却:35s-34s\n系数:10.64(野兽11.7)",
    "风信鹤羽": "风信鹤羽\n冷却:35s-34s-32.5s\n系数:11.02",
    "岚·不鸣之刃": "岚·不鸣之刃\n冷却:36s-35s-33.5s\n系数:11.89(野兽13.08)",
    "风月含袖": "风月含袖\n冷却:36s-35s-33.5s\n系数:12.8/13.51(机械14.08/14.86)",
    "尽滅": "尽滅\n冷却:36s-35s-33.5s\n系数:13.637/14.214(人类14.999/15.64)"
}